{
  "hash": "bec02085",
  "configHash": "e1392405",
  "lockfileHash": "ce02b62f",
  "browserHash": "6d73da35",
  "optimized": {
    "vue": {
      "src": "../../../../node_modules/vue/dist/vue.runtime.esm-bundler.js",
      "file": "vue.js",
      "fileHash": "e4611548",
      "needsInterop": false
    },
    "vitepress > @vue/devtools-api": {
      "src": "../../../../node_modules/@vue/devtools-api/dist/index.js",
      "file": "vitepress___@vue_devtools-api.js",
      "fileHash": "6d3b59c2",
      "needsInterop": false
    },
    "vitepress > @vueuse/core": {
      "src": "../../../../node_modules/@vueuse/core/index.mjs",
      "file": "vitepress___@vueuse_core.js",
      "fileHash": "80049e4c",
      "needsInterop": false
    },
    "medium-zoom": {
      "src": "../../../../node_modules/medium-zoom/dist/medium-zoom.esm.js",
      "file": "medium-zoom.js",
      "fileHash": "2c8596f4",
      "needsInterop": false
    },
    "@escook/vitepress-theme": {
      "src": "../../../../node_modules/@escook/vitepress-theme/dist/index.js",
      "file": "@escook_vitepress-theme.js",
      "fileHash": "e4ffbd63",
      "needsInterop": false
    },
    "dayjs": {
      "src": "../../../../node_modules/dayjs/dayjs.min.js",
      "file": "dayjs.js",
      "fileHash": "2e2f36ff",
      "needsInterop": true
    },
    "dayjs/plugin/utc.js": {
      "src": "../../../../node_modules/dayjs/plugin/utc.js",
      "file": "dayjs_plugin_utc__js.js",
      "fileHash": "d2f21688",
      "needsInterop": true
    },
    "dayjs/plugin/relativeTime": {
      "src": "../../../../node_modules/dayjs/plugin/relativeTime.js",
      "file": "dayjs_plugin_relativeTime.js",
      "fileHash": "84587270",
      "needsInterop": true
    },
    "dayjs/locale/zh-cn": {
      "src": "../../../../node_modules/dayjs/locale/zh-cn.js",
      "file": "dayjs_locale_zh-cn.js",
      "fileHash": "1eff9d89",
      "needsInterop": true
    }
  },
  "chunks": {
    "EscookMusicBall-BkDBnoZh-27SF6KT4": {
      "file": "EscookMusicBall-BkDBnoZh-27SF6KT4.js"
    },
    "chunk-O3YQPVDG": {
      "file": "chunk-O3YQPVDG.js"
    },
    "EscookHomeFeatureBefore-D_e5sYrO-2ZBQS3UJ": {
      "file": "EscookHomeFeatureBefore-D_e5sYrO-2ZBQS3UJ.js"
    },
    "EscookConfetti-BU05OPRV-7IQ6UN2A": {
      "file": "EscookConfetti-BU05OPRV-7IQ6UN2A.js"
    },
    "chunk-UPL7KAOW": {
      "file": "chunk-UPL7KAOW.js"
    },
    "chunk-YCYCIHK5": {
      "file": "chunk-YCYCIHK5.js"
    },
    "chunk-5WRI5ZAA": {
      "file": "chunk-5WRI5ZAA.js"
    }
  }
}